setup.py
build/lib/dpimport/__init__.py
build/lib/dpimport/__version__.py
build/lib/dpimport/database/__init__.py
build/lib/dpimport/patterns/__init__.py
build/lib/tools/__init__.py
build/lib/tools/database/__init__.py
build/lib/tools/reader/__init__.py
build/scripts-3.11/import.py
dpimport/__init__.py
dpimport/__version__.py
dpimport/database/__init__.py
dpimport/patterns/__init__.py
scripts/import.py
tools/__init__.py
tools/database/__init__.py
tools/reader/__init__.py
dpimport_test_2-1.0.6.dist-info/METADATA
dpimport_test_2-1.0.6.dist-info/WHEEL
dpimport_test_2-1.0.6.dist-info/RECORD
