Metadata-Version: 2.1
Name: dpimport_test_2
Version: 1.0.6
Summary: DPdash importer
Project-URL: Homepage, https://github.com/harvard-nrg/dpimport
Author-email: Neuroinformatics Research Group <info@neuroinfo.org>
Requires-Dist: pandas
Requires-Dist: pymongo==3.11.4
